LICENSE.txt
MANIFEST.in
README.rst
requirements.txt
setup.cfg
setup.py
shiver_me_tinders/__init__.py
shiver_me_tinders/tinder.py
shiver_me_tinders.egg-info/PKG-INFO
shiver_me_tinders.egg-info/SOURCES.txt
shiver_me_tinders.egg-info/dependency_links.txt
shiver_me_tinders.egg-info/requires.txt
shiver_me_tinders.egg-info/top_level.txt
shiver_me_tinders.egg-info/zip-safe