Metadata-Version: 1.1
Name: shiver-me-tinders
Version: 0.1.2
Summary: A lightweight wrapper around Tinder's API.
Home-page: https://github.com/nficano/shiver-me-tinders
Author: Nick Ficano
Author-email: nficano@gmail.com
License: Copyright (c) 2015 Nick Ficano (http://nickficano.com)
